textual_inputs/__init__.py
textual_inputs/events.py
textual_inputs/integer_input.py
textual_inputs/text_input.py
textual_inputs-0.2.6.dist-info/LICENSE
textual_inputs-0.2.6.dist-info/METADATA
textual_inputs-0.2.6.dist-info/WHEEL
textual_inputs-0.2.6.dist-info/top_level.txt
textual_inputs-0.2.6.dist-info/RECORD
