Metadata-Version: 2.1
Name: textual-inputs
Version: 0.2.6
Summary: textual-inputs is a collection of input widgets for the Textual TUI framework
Author-email: 57846408+sirfuzzalot@users.noreply.github.com
License: MIT
Project-URL: Source, https://github.com/sirfuzzalot/textual-inputs
Project-URL: Documentation, https://github.com/sirfuzzalot/textual-inputs
Project-URL: Tracker, https://github.com/sirfuzzalot/textual-inputs/issues
Keywords: tui,terminal,widget
Classifier: Development Status :: 2 - Pre-Alpha
Classifier: License :: OSI Approved :: MIT License
Classifier: Environment :: Console
Classifier: Intended Audience :: Developers
Classifier: Operating System :: MacOS
Classifier: Operating System :: POSIX :: Linux
Classifier: Programming Language :: Python
Classifier: Programming Language :: Python :: 3
Classifier: Programming Language :: Python :: 3 :: Only
Classifier: Programming Language :: Python :: 3.7
Classifier: Programming Language :: Python :: 3.8
Classifier: Programming Language :: Python :: 3.9
Classifier: Programming Language :: Python :: 3.10
Requires-Python: >=3.7
License-File: LICENSE
Requires-Dist: textual (<0.2,>=0.1.18)
